{
  "sites": [
    {
      "name": "Power#3745",
      "url": "https://507ab6b2-a51f-490e-9363-960390d518db-00-3pgweb6uweae0.pike.replit.dev/",
      "checkInterval": 5,
      "status": "down",
      "uptime": 0,
      "responseTime": -1,
      "lastChecked": "2026-01-08T19:50:03.445Z",
      "history": [
        {
          "timestamp": "2026-01-06T19:54:33.286Z",
          "status": "down",
          "responseTime": -1
        },
        {
          "timestamp": "2026-01-06T20:23:29.754Z",
          "status": "down",
          "responseTime": -1
        },
        {
          "timestamp": "2026-01-06T20:44:26.246Z",
          "status": "down",
          "responseTime": -1
        },
        {
          "timestamp": "2026-01-06T20:55:22.210Z",
          "status": "down",
          "responseTime": -1
        },
        {
          "timestamp": "2026-01-06T21:22:35.379Z",
          "status": "down",
          "responseTime": -1
        },
        {
          "timestamp": "2026-01-06T21:40:54.306Z",
          "status": "down",
          "responseTime": -1
        },
        {
          "timestamp": "2026-01-06T21:53:05.327Z",
          "status": "down",
          "responseTime": -1
        },
        {
          "timestamp": "2026-01-06T22:17:00.518Z",
          "status": "down",
          "responseTime": -1
        },
        {
          "timestamp": "2026-01-06T22:41:51.795Z",
          "status": "down",
          "responseTime": -1
        },
        {
          "timestamp": "2026-01-06T22:55:16.570Z",
          "status": "down",
          "responseTime": -1
        },
        {
          "timestamp": "2026-01-06T23:22:36.509Z",
          "status": "down",
          "responseTime": -1
        },
        {
          "timestamp": "2026-01-06T23:39:53.907Z",
          "status": "down",
          "responseTime": -1
        },
        {
          "timestamp": "2026-01-06T23:50:53.858Z",
          "status": "down",
          "responseTime": -1
        },
        {
          "timestamp": "2026-01-07T00:56:59.919Z",
          "status": "down",
          "responseTime": -1
        },
        {
          "timestamp": "2026-01-07T02:59:30.708Z",
          "status": "down",
          "responseTime": -1
        },
        {
          "timestamp": "2026-01-07T04:06:18.397Z",
          "status": "down",
          "responseTime": -1
        },
        {
          "timestamp": "2026-01-07T04:51:43.795Z",
          "status": "down",
          "responseTime": -1
        },
        {
          "timestamp": "2026-01-07T05:19:15.591Z",
          "status": "down",
          "responseTime": -1
        },
        {
          "timestamp": "2026-01-07T05:45:20.216Z",
          "status": "down",
          "responseTime": -1
        },
        {
          "timestamp": "2026-01-07T05:57:22.121Z",
          "status": "down",
          "responseTime": -1
        },
        {
          "timestamp": "2026-01-07T06:44:33.635Z",
          "status": "down",
          "responseTime": -1
        },
        {
          "timestamp": "2026-01-07T07:03:39.489Z",
          "status": "down",
          "responseTime": -1
        },
        {
          "timestamp": "2026-01-07T07:35:00.239Z",
          "status": "down",
          "responseTime": -1
        },
        {
          "timestamp": "2026-01-07T07:51:03.451Z",
          "status": "down",
          "responseTime": -1
        },
        {
          "timestamp": "2026-01-07T08:17:54.781Z",
          "status": "down",
          "responseTime": -1
        },
        {
          "timestamp": "2026-01-07T08:49:41.069Z",
          "status": "down",
          "responseTime": -1
        },
        {
          "timestamp": "2026-01-07T09:16:23.931Z",
          "status": "down",
          "responseTime": -1
        },
        {
          "timestamp": "2026-01-07T09:45:02.967Z",
          "status": "down",
          "responseTime": -1
        },
        {
          "timestamp": "2026-01-07T09:58:01.784Z",
          "status": "down",
          "responseTime": -1
        },
        {
          "timestamp": "2026-01-07T10:34:24.741Z",
          "status": "down",
          "responseTime": -1
        },
        {
          "timestamp": "2026-01-07T10:53:43.004Z",
          "status": "down",
          "responseTime": -1
        },
        {
          "timestamp": "2026-01-07T11:17:56.894Z",
          "status": "down",
          "responseTime": -1
        },
        {
          "timestamp": "2026-01-07T11:36:46.645Z",
          "status": "down",
          "responseTime": -1
        },
        {
          "timestamp": "2026-01-07T11:49:50.373Z",
          "status": "down",
          "responseTime": -1
        },
        {
          "timestamp": "2026-01-07T12:01:00.833Z",
          "status": "down",
          "responseTime": -1
        },
        {
          "timestamp": "2026-01-07T13:04:21.988Z",
          "status": "down",
          "responseTime": -1
        },
        {
          "timestamp": "2026-01-07T13:48:59.676Z",
          "status": "down",
          "responseTime": -1
        },
        {
          "timestamp": "2026-01-07T14:11:43.496Z",
          "status": "down",
          "responseTime": -1
        },
        {
          "timestamp": "2026-01-07T14:44:01.386Z",
          "status": "down",
          "responseTime": -1
        },
        {
          "timestamp": "2026-01-07T14:59:44.957Z",
          "status": "down",
          "responseTime": -1
        },
        {
          "timestamp": "2026-01-07T15:35:34.070Z",
          "status": "down",
          "responseTime": -1
        },
        {
          "timestamp": "2026-01-07T15:54:16.285Z",
          "status": "down",
          "responseTime": -1
        },
        {
          "timestamp": "2026-01-07T16:28:41.796Z",
          "status": "down",
          "responseTime": -1
        },
        {
          "timestamp": "2026-01-07T16:57:59.958Z",
          "status": "down",
          "responseTime": -1
        },
        {
          "timestamp": "2026-01-07T17:34:04.291Z",
          "status": "down",
          "responseTime": -1
        },
        {
          "timestamp": "2026-01-07T17:53:03.753Z",
          "status": "down",
          "responseTime": -1
        },
        {
          "timestamp": "2026-01-07T18:26:14.232Z",
          "status": "down",
          "responseTime": -1
        },
        {
          "timestamp": "2026-01-07T18:56:24.134Z",
          "status": "down",
          "responseTime": -1
        },
        {
          "timestamp": "2026-01-07T19:24:03.916Z",
          "status": "down",
          "responseTime": -1
        },
        {
          "timestamp": "2026-01-07T19:40:30.605Z",
          "status": "down",
          "responseTime": -1
        },
        {
          "timestamp": "2026-01-07T19:51:58.507Z",
          "status": "down",
          "responseTime": -1
        },
        {
          "timestamp": "2026-01-07T20:16:45.596Z",
          "status": "down",
          "responseTime": -1
        },
        {
          "timestamp": "2026-01-07T20:43:10.822Z",
          "status": "down",
          "responseTime": -1
        },
        {
          "timestamp": "2026-01-07T20:58:33.443Z",
          "status": "down",
          "responseTime": -1
        },
        {
          "timestamp": "2026-01-07T21:28:56.729Z",
          "status": "down",
          "responseTime": -1
        },
        {
          "timestamp": "2026-01-07T21:45:16.494Z",
          "status": "down",
          "responseTime": -1
        },
        {
          "timestamp": "2026-01-07T21:56:06.748Z",
          "status": "down",
          "responseTime": -1
        },
        {
          "timestamp": "2026-01-07T22:25:06.203Z",
          "status": "down",
          "responseTime": -1
        },
        {
          "timestamp": "2026-01-07T22:45:51.240Z",
          "status": "down",
          "responseTime": -1
        },
        {
          "timestamp": "2026-01-07T22:57:18.569Z",
          "status": "down",
          "responseTime": -1
        },
        {
          "timestamp": "2026-01-07T23:27:41.589Z",
          "status": "down",
          "responseTime": -1
        },
        {
          "timestamp": "2026-01-07T23:43:58.827Z",
          "status": "down",
          "responseTime": -1
        },
        {
          "timestamp": "2026-01-07T23:55:01.316Z",
          "status": "down",
          "responseTime": -1
        },
        {
          "timestamp": "2026-01-08T01:48:48.575Z",
          "status": "down",
          "responseTime": -1
        },
        {
          "timestamp": "2026-01-08T03:20:42.138Z",
          "status": "down",
          "responseTime": -1
        },
        {
          "timestamp": "2026-01-08T04:12:07.902Z",
          "status": "down",
          "responseTime": -1
        },
        {
          "timestamp": "2026-01-08T04:53:13.222Z",
          "status": "down",
          "responseTime": -1
        },
        {
          "timestamp": "2026-01-08T05:21:28.606Z",
          "status": "down",
          "responseTime": -1
        },
        {
          "timestamp": "2026-01-08T05:46:08.843Z",
          "status": "down",
          "responseTime": -1
        },
        {
          "timestamp": "2026-01-08T05:57:56.494Z",
          "status": "down",
          "responseTime": -1
        },
        {
          "timestamp": "2026-01-08T06:47:09.599Z",
          "status": "down",
          "responseTime": -1
        },
        {
          "timestamp": "2026-01-08T07:13:35.890Z",
          "status": "down",
          "responseTime": -1
        },
        {
          "timestamp": "2026-01-08T07:39:23.389Z",
          "status": "down",
          "responseTime": -1
        },
        {
          "timestamp": "2026-01-08T07:52:40.332Z",
          "status": "down",
          "responseTime": -1
        },
        {
          "timestamp": "2026-01-08T08:23:31.936Z",
          "status": "down",
          "responseTime": -1
        },
        {
          "timestamp": "2026-01-08T08:53:44.148Z",
          "status": "down",
          "responseTime": -1
        },
        {
          "timestamp": "2026-01-08T09:26:17.337Z",
          "status": "down",
          "responseTime": -1
        },
        {
          "timestamp": "2026-01-08T09:50:50.824Z",
          "status": "down",
          "responseTime": -1
        },
        {
          "timestamp": "2026-01-08T10:14:27.145Z",
          "status": "down",
          "responseTime": -1
        },
        {
          "timestamp": "2026-01-08T10:45:12.782Z",
          "status": "down",
          "responseTime": -1
        },
        {
          "timestamp": "2026-01-08T10:59:16.214Z",
          "status": "down",
          "responseTime": -1
        },
        {
          "timestamp": "2026-01-08T11:29:33.983Z",
          "status": "down",
          "responseTime": -1
        },
        {
          "timestamp": "2026-01-08T11:46:06.625Z",
          "status": "down",
          "responseTime": -1
        },
        {
          "timestamp": "2026-01-08T11:57:12.500Z",
          "status": "down",
          "responseTime": -1
        },
        {
          "timestamp": "2026-01-08T12:59:55.551Z",
          "status": "down",
          "responseTime": -1
        },
        {
          "timestamp": "2026-01-08T13:47:47.741Z",
          "status": "down",
          "responseTime": -1
        },
        {
          "timestamp": "2026-01-08T14:12:27.751Z",
          "status": "down",
          "responseTime": -1
        },
        {
          "timestamp": "2026-01-08T14:46:12.052Z",
          "status": "down",
          "responseTime": -1
        },
        {
          "timestamp": "2026-01-08T15:01:35.959Z",
          "status": "down",
          "responseTime": -1
        },
        {
          "timestamp": "2026-01-08T15:36:45.481Z",
          "status": "down",
          "responseTime": -1
        },
        {
          "timestamp": "2026-01-08T15:55:58.892Z",
          "status": "down",
          "responseTime": -1
        },
        {
          "timestamp": "2026-01-08T16:34:46.842Z",
          "status": "down",
          "responseTime": -1
        },
        {
          "timestamp": "2026-01-08T17:00:37.162Z",
          "status": "down",
          "responseTime": -1
        },
        {
          "timestamp": "2026-01-08T17:36:25.755Z",
          "status": "down",
          "responseTime": -1
        },
        {
          "timestamp": "2026-01-08T17:55:27.483Z",
          "status": "down",
          "responseTime": -1
        },
        {
          "timestamp": "2026-01-08T18:31:16.046Z",
          "status": "down",
          "responseTime": -1
        },
        {
          "timestamp": "2026-01-08T18:56:16.823Z",
          "status": "down",
          "responseTime": -1
        },
        {
          "timestamp": "2026-01-08T19:23:12.037Z",
          "status": "down",
          "responseTime": -1
        },
        {
          "timestamp": "2026-01-08T19:38:58.844Z",
          "status": "down",
          "responseTime": -1
        },
        {
          "timestamp": "2026-01-08T19:50:03.445Z",
          "status": "down",
          "responseTime": -1
        }
      ]
    }
  ],
  "lastUpdated": "2026-01-08T19:50:03.445Z"
}