{
  "sites": [
    {
      "name": "Power#3745",
      "url": "https://507ab6b2-a51f-490e-9363-960390d518db-00-3pgweb6uweae0.pike.replit.dev/",
      "checkInterval": 5,
      "status": "down",
      "uptime": 0,
      "responseTime": -1,
      "lastChecked": "2025-11-22T19:50:10.241Z",
      "history": [
        {
          "timestamp": "2025-11-21T11:53:12.182Z",
          "status": "down",
          "responseTime": -1
        },
        {
          "timestamp": "2025-11-21T12:32:19.421Z",
          "status": "down",
          "responseTime": -1
        },
        {
          "timestamp": "2025-11-21T13:08:06.450Z",
          "status": "down",
          "responseTime": -1
        },
        {
          "timestamp": "2025-11-21T13:38:04.548Z",
          "status": "down",
          "responseTime": -1
        },
        {
          "timestamp": "2025-11-21T13:50:17.241Z",
          "status": "down",
          "responseTime": -1
        },
        {
          "timestamp": "2025-11-21T14:09:34.521Z",
          "status": "down",
          "responseTime": -1
        },
        {
          "timestamp": "2025-11-21T14:33:43.864Z",
          "status": "down",
          "responseTime": -1
        },
        {
          "timestamp": "2025-11-21T14:47:36.472Z",
          "status": "down",
          "responseTime": -1
        },
        {
          "timestamp": "2025-11-21T14:58:14.076Z",
          "status": "down",
          "responseTime": -1
        },
        {
          "timestamp": "2025-11-21T15:24:51.312Z",
          "status": "down",
          "responseTime": -1
        },
        {
          "timestamp": "2025-11-21T15:37:00.893Z",
          "status": "down",
          "responseTime": -1
        },
        {
          "timestamp": "2025-11-21T15:47:53.720Z",
          "status": "down",
          "responseTime": -1
        },
        {
          "timestamp": "2025-11-21T15:58:49.514Z",
          "status": "down",
          "responseTime": -1
        },
        {
          "timestamp": "2025-11-21T16:33:09.165Z",
          "status": "down",
          "responseTime": -1
        },
        {
          "timestamp": "2025-11-21T16:50:04.678Z",
          "status": "down",
          "responseTime": -1
        },
        {
          "timestamp": "2025-11-21T17:07:53.598Z",
          "status": "down",
          "responseTime": -1
        },
        {
          "timestamp": "2025-11-21T17:30:24.664Z",
          "status": "down",
          "responseTime": -1
        },
        {
          "timestamp": "2025-11-21T17:44:14.402Z",
          "status": "down",
          "responseTime": -1
        },
        {
          "timestamp": "2025-11-21T17:55:17.744Z",
          "status": "down",
          "responseTime": -1
        },
        {
          "timestamp": "2025-11-21T18:28:04.952Z",
          "status": "down",
          "responseTime": -1
        },
        {
          "timestamp": "2025-11-21T18:48:30.988Z",
          "status": "down",
          "responseTime": -1
        },
        {
          "timestamp": "2025-11-21T18:59:19.211Z",
          "status": "down",
          "responseTime": -1
        },
        {
          "timestamp": "2025-11-21T19:23:14.405Z",
          "status": "down",
          "responseTime": -1
        },
        {
          "timestamp": "2025-11-21T19:35:32.525Z",
          "status": "down",
          "responseTime": -1
        },
        {
          "timestamp": "2025-11-21T19:46:39.640Z",
          "status": "down",
          "responseTime": -1
        },
        {
          "timestamp": "2025-11-21T19:57:32.683Z",
          "status": "down",
          "responseTime": -1
        },
        {
          "timestamp": "2025-11-21T20:29:22.421Z",
          "status": "down",
          "responseTime": -1
        },
        {
          "timestamp": "2025-11-21T20:44:13.076Z",
          "status": "down",
          "responseTime": -1
        },
        {
          "timestamp": "2025-11-21T20:55:05.986Z",
          "status": "down",
          "responseTime": -1
        },
        {
          "timestamp": "2025-11-21T21:18:12.773Z",
          "status": "down",
          "responseTime": -1
        },
        {
          "timestamp": "2025-11-21T21:32:15.020Z",
          "status": "down",
          "responseTime": -1
        },
        {
          "timestamp": "2025-11-21T21:43:20.837Z",
          "status": "down",
          "responseTime": -1
        },
        {
          "timestamp": "2025-11-21T21:54:07.445Z",
          "status": "down",
          "responseTime": -1
        },
        {
          "timestamp": "2025-11-21T22:17:50.362Z",
          "status": "down",
          "responseTime": -1
        },
        {
          "timestamp": "2025-11-21T22:37:45.729Z",
          "status": "down",
          "responseTime": -1
        },
        {
          "timestamp": "2025-11-21T22:48:54.241Z",
          "status": "down",
          "responseTime": -1
        },
        {
          "timestamp": "2025-11-21T22:59:47.599Z",
          "status": "down",
          "responseTime": -1
        },
        {
          "timestamp": "2025-11-21T23:25:18.031Z",
          "status": "down",
          "responseTime": -1
        },
        {
          "timestamp": "2025-11-21T23:38:47.161Z",
          "status": "down",
          "responseTime": -1
        },
        {
          "timestamp": "2025-11-21T23:49:49.508Z",
          "status": "down",
          "responseTime": -1
        },
        {
          "timestamp": "2025-11-22T00:38:37.959Z",
          "status": "down",
          "responseTime": -1
        },
        {
          "timestamp": "2025-11-22T02:15:37.818Z",
          "status": "down",
          "responseTime": -1
        },
        {
          "timestamp": "2025-11-22T03:15:04.986Z",
          "status": "down",
          "responseTime": -1
        },
        {
          "timestamp": "2025-11-22T03:46:19.990Z",
          "status": "down",
          "responseTime": -1
        },
        {
          "timestamp": "2025-11-22T03:57:20.721Z",
          "status": "down",
          "responseTime": -1
        },
        {
          "timestamp": "2025-11-22T04:28:52.555Z",
          "status": "down",
          "responseTime": -1
        },
        {
          "timestamp": "2025-11-22T04:44:33.802Z",
          "status": "down",
          "responseTime": -1
        },
        {
          "timestamp": "2025-11-22T04:55:22.304Z",
          "status": "down",
          "responseTime": -1
        },
        {
          "timestamp": "2025-11-22T05:19:33.481Z",
          "status": "down",
          "responseTime": -1
        },
        {
          "timestamp": "2025-11-22T05:37:14.249Z",
          "status": "down",
          "responseTime": -1
        },
        {
          "timestamp": "2025-11-22T05:47:49.594Z",
          "status": "down",
          "responseTime": -1
        },
        {
          "timestamp": "2025-11-22T05:58:29.537Z",
          "status": "down",
          "responseTime": -1
        },
        {
          "timestamp": "2025-11-22T06:36:46.613Z",
          "status": "down",
          "responseTime": -1
        },
        {
          "timestamp": "2025-11-22T06:51:48.147Z",
          "status": "down",
          "responseTime": -1
        },
        {
          "timestamp": "2025-11-22T07:11:45.155Z",
          "status": "down",
          "responseTime": -1
        },
        {
          "timestamp": "2025-11-22T07:28:44.589Z",
          "status": "down",
          "responseTime": -1
        },
        {
          "timestamp": "2025-11-22T07:40:04.330Z",
          "status": "down",
          "responseTime": -1
        },
        {
          "timestamp": "2025-11-22T07:50:59.621Z",
          "status": "down",
          "responseTime": -1
        },
        {
          "timestamp": "2025-11-22T08:13:46.087Z",
          "status": "down",
          "responseTime": -1
        },
        {
          "timestamp": "2025-11-22T08:39:09.250Z",
          "status": "down",
          "responseTime": -1
        },
        {
          "timestamp": "2025-11-22T08:52:28.733Z",
          "status": "down",
          "responseTime": -1
        },
        {
          "timestamp": "2025-11-22T09:13:28.838Z",
          "status": "down",
          "responseTime": -1
        },
        {
          "timestamp": "2025-11-22T09:31:23.308Z",
          "status": "down",
          "responseTime": -1
        },
        {
          "timestamp": "2025-11-22T09:42:22.762Z",
          "status": "down",
          "responseTime": -1
        },
        {
          "timestamp": "2025-11-22T09:53:12.240Z",
          "status": "down",
          "responseTime": -1
        },
        {
          "timestamp": "2025-11-22T10:15:26.600Z",
          "status": "down",
          "responseTime": -1
        },
        {
          "timestamp": "2025-11-22T10:34:51.428Z",
          "status": "down",
          "responseTime": -1
        },
        {
          "timestamp": "2025-11-22T10:45:41.449Z",
          "status": "down",
          "responseTime": -1
        },
        {
          "timestamp": "2025-11-22T10:56:34.445Z",
          "status": "down",
          "responseTime": -1
        },
        {
          "timestamp": "2025-11-22T11:17:37.552Z",
          "status": "down",
          "responseTime": -1
        },
        {
          "timestamp": "2025-11-22T11:28:25.697Z",
          "status": "down",
          "responseTime": -1
        },
        {
          "timestamp": "2025-11-22T11:40:19.396Z",
          "status": "down",
          "responseTime": -1
        },
        {
          "timestamp": "2025-11-22T11:51:10.013Z",
          "status": "down",
          "responseTime": -1
        },
        {
          "timestamp": "2025-11-22T12:19:05.095Z",
          "status": "down",
          "responseTime": -1
        },
        {
          "timestamp": "2025-11-22T12:55:51.123Z",
          "status": "down",
          "responseTime": -1
        },
        {
          "timestamp": "2025-11-22T13:25:26.438Z",
          "status": "down",
          "responseTime": -1
        },
        {
          "timestamp": "2025-11-22T13:39:42.791Z",
          "status": "down",
          "responseTime": -1
        },
        {
          "timestamp": "2025-11-22T13:50:33.657Z",
          "status": "down",
          "responseTime": -1
        },
        {
          "timestamp": "2025-11-22T14:08:23.201Z",
          "status": "down",
          "responseTime": -1
        },
        {
          "timestamp": "2025-11-22T14:29:36.964Z",
          "status": "down",
          "responseTime": -1
        },
        {
          "timestamp": "2025-11-22T14:42:36.756Z",
          "status": "down",
          "responseTime": -1
        },
        {
          "timestamp": "2025-11-22T14:53:19.499Z",
          "status": "down",
          "responseTime": -1
        },
        {
          "timestamp": "2025-11-22T15:14:16.418Z",
          "status": "down",
          "responseTime": -1
        },
        {
          "timestamp": "2025-11-22T15:30:50.915Z",
          "status": "down",
          "responseTime": -1
        },
        {
          "timestamp": "2025-11-22T15:42:09.784Z",
          "status": "down",
          "responseTime": -1
        },
        {
          "timestamp": "2025-11-22T15:53:35.216Z",
          "status": "down",
          "responseTime": -1
        },
        {
          "timestamp": "2025-11-22T16:19:02.086Z",
          "status": "down",
          "responseTime": -1
        },
        {
          "timestamp": "2025-11-22T16:40:37.502Z",
          "status": "down",
          "responseTime": -1
        },
        {
          "timestamp": "2025-11-22T16:52:16.488Z",
          "status": "down",
          "responseTime": -1
        },
        {
          "timestamp": "2025-11-22T17:11:10.580Z",
          "status": "down",
          "responseTime": -1
        },
        {
          "timestamp": "2025-11-22T17:29:33.000Z",
          "status": "down",
          "responseTime": -1
        },
        {
          "timestamp": "2025-11-22T17:41:35.487Z",
          "status": "down",
          "responseTime": -1
        },
        {
          "timestamp": "2025-11-22T17:52:41.613Z",
          "status": "down",
          "responseTime": -1
        },
        {
          "timestamp": "2025-11-22T18:19:36.047Z",
          "status": "down",
          "responseTime": -1
        },
        {
          "timestamp": "2025-11-22T18:47:22.509Z",
          "status": "down",
          "responseTime": -1
        },
        {
          "timestamp": "2025-11-22T18:55:21.943Z",
          "status": "down",
          "responseTime": -1
        },
        {
          "timestamp": "2025-11-22T19:15:25.237Z",
          "status": "down",
          "responseTime": -1
        },
        {
          "timestamp": "2025-11-22T19:27:06.541Z",
          "status": "down",
          "responseTime": -1
        },
        {
          "timestamp": "2025-11-22T19:39:35.841Z",
          "status": "down",
          "responseTime": -1
        },
        {
          "timestamp": "2025-11-22T19:50:10.241Z",
          "status": "down",
          "responseTime": -1
        }
      ]
    }
  ],
  "lastUpdated": "2025-11-22T19:50:10.241Z"
}