{
  "sites": [
    {
      "name": "Power#3745",
      "url": "https://507ab6b2-a51f-490e-9363-960390d518db-00-3pgweb6uweae0.pike.replit.dev/",
      "checkInterval": 5,
      "status": "down",
      "uptime": 0,
      "responseTime": -1,
      "lastChecked": "2025-11-28T19:29:42.125Z",
      "history": [
        {
          "timestamp": "2025-11-27T08:32:54.538Z",
          "status": "down",
          "responseTime": -1
        },
        {
          "timestamp": "2025-11-27T08:53:49.664Z",
          "status": "down",
          "responseTime": -1
        },
        {
          "timestamp": "2025-11-27T09:20:05.826Z",
          "status": "down",
          "responseTime": -1
        },
        {
          "timestamp": "2025-11-27T09:39:35.297Z",
          "status": "down",
          "responseTime": -1
        },
        {
          "timestamp": "2025-11-27T09:51:31.252Z",
          "status": "down",
          "responseTime": -1
        },
        {
          "timestamp": "2025-11-27T10:14:12.138Z",
          "status": "down",
          "responseTime": -1
        },
        {
          "timestamp": "2025-11-27T10:41:43.466Z",
          "status": "down",
          "responseTime": -1
        },
        {
          "timestamp": "2025-11-27T10:53:56.817Z",
          "status": "down",
          "responseTime": -1
        },
        {
          "timestamp": "2025-11-27T11:16:26.966Z",
          "status": "down",
          "responseTime": -1
        },
        {
          "timestamp": "2025-11-27T11:32:39.798Z",
          "status": "down",
          "responseTime": -1
        },
        {
          "timestamp": "2025-11-27T11:44:39.039Z",
          "status": "down",
          "responseTime": -1
        },
        {
          "timestamp": "2025-11-27T11:55:16.632Z",
          "status": "down",
          "responseTime": -1
        },
        {
          "timestamp": "2025-11-27T12:44:54.036Z",
          "status": "down",
          "responseTime": -1
        },
        {
          "timestamp": "2025-11-27T13:22:44.542Z",
          "status": "down",
          "responseTime": -1
        },
        {
          "timestamp": "2025-11-27T13:48:09.942Z",
          "status": "down",
          "responseTime": -1
        },
        {
          "timestamp": "2025-11-27T13:59:20.121Z",
          "status": "down",
          "responseTime": -1
        },
        {
          "timestamp": "2025-11-27T14:29:55.648Z",
          "status": "down",
          "responseTime": -1
        },
        {
          "timestamp": "2025-11-27T14:47:13.613Z",
          "status": "down",
          "responseTime": -1
        },
        {
          "timestamp": "2025-11-27T14:58:10.156Z",
          "status": "down",
          "responseTime": -1
        },
        {
          "timestamp": "2025-11-27T15:28:43.506Z",
          "status": "down",
          "responseTime": -1
        },
        {
          "timestamp": "2025-11-27T15:44:20.460Z",
          "status": "down",
          "responseTime": -1
        },
        {
          "timestamp": "2025-11-27T15:55:40.766Z",
          "status": "down",
          "responseTime": -1
        },
        {
          "timestamp": "2025-11-27T16:27:43.117Z",
          "status": "down",
          "responseTime": -1
        },
        {
          "timestamp": "2025-11-27T16:49:14.844Z",
          "status": "down",
          "responseTime": -1
        },
        {
          "timestamp": "2025-11-27T17:00:26.104Z",
          "status": "down",
          "responseTime": -1
        },
        {
          "timestamp": "2025-11-27T17:25:34.981Z",
          "status": "down",
          "responseTime": -1
        },
        {
          "timestamp": "2025-11-27T17:40:13.894Z",
          "status": "down",
          "responseTime": -1
        },
        {
          "timestamp": "2025-11-27T17:50:50.902Z",
          "status": "down",
          "responseTime": -1
        },
        {
          "timestamp": "2025-11-27T18:15:28.965Z",
          "status": "down",
          "responseTime": -1
        },
        {
          "timestamp": "2025-11-27T18:44:10.342Z",
          "status": "down",
          "responseTime": -1
        },
        {
          "timestamp": "2025-11-27T18:56:06.452Z",
          "status": "down",
          "responseTime": -1
        },
        {
          "timestamp": "2025-11-27T19:18:21.562Z",
          "status": "down",
          "responseTime": -1
        },
        {
          "timestamp": "2025-11-27T19:29:27.771Z",
          "status": "down",
          "responseTime": -1
        },
        {
          "timestamp": "2025-11-27T19:40:48.775Z",
          "status": "down",
          "responseTime": -1
        },
        {
          "timestamp": "2025-11-27T19:51:57.950Z",
          "status": "down",
          "responseTime": -1
        },
        {
          "timestamp": "2025-11-27T20:12:59.327Z",
          "status": "down",
          "responseTime": -1
        },
        {
          "timestamp": "2025-11-27T20:32:35.371Z",
          "status": "down",
          "responseTime": -1
        },
        {
          "timestamp": "2025-11-27T20:44:51.508Z",
          "status": "down",
          "responseTime": -1
        },
        {
          "timestamp": "2025-11-27T20:55:38.301Z",
          "status": "down",
          "responseTime": -1
        },
        {
          "timestamp": "2025-11-27T21:19:11.767Z",
          "status": "down",
          "responseTime": -1
        },
        {
          "timestamp": "2025-11-27T21:32:26.815Z",
          "status": "down",
          "responseTime": -1
        },
        {
          "timestamp": "2025-11-27T21:43:24.685Z",
          "status": "down",
          "responseTime": -1
        },
        {
          "timestamp": "2025-11-27T21:54:25.698Z",
          "status": "down",
          "responseTime": -1
        },
        {
          "timestamp": "2025-11-27T22:17:51.341Z",
          "status": "down",
          "responseTime": -1
        },
        {
          "timestamp": "2025-11-27T22:37:09.126Z",
          "status": "down",
          "responseTime": -1
        },
        {
          "timestamp": "2025-11-27T22:48:00.359Z",
          "status": "down",
          "responseTime": -1
        },
        {
          "timestamp": "2025-11-27T22:58:49.239Z",
          "status": "down",
          "responseTime": -1
        },
        {
          "timestamp": "2025-11-27T23:25:08.222Z",
          "status": "down",
          "responseTime": -1
        },
        {
          "timestamp": "2025-11-27T23:39:02.157Z",
          "status": "down",
          "responseTime": -1
        },
        {
          "timestamp": "2025-11-27T23:49:58.518Z",
          "status": "down",
          "responseTime": -1
        },
        {
          "timestamp": "2025-11-28T00:41:12.217Z",
          "status": "down",
          "responseTime": -1
        },
        {
          "timestamp": "2025-11-28T02:21:19.959Z",
          "status": "down",
          "responseTime": -1
        },
        {
          "timestamp": "2025-11-28T03:31:29.527Z",
          "status": "down",
          "responseTime": -1
        },
        {
          "timestamp": "2025-11-28T03:57:28.029Z",
          "status": "down",
          "responseTime": -1
        },
        {
          "timestamp": "2025-11-28T04:31:58.844Z",
          "status": "down",
          "responseTime": -1
        },
        {
          "timestamp": "2025-11-28T04:49:15.752Z",
          "status": "down",
          "responseTime": -1
        },
        {
          "timestamp": "2025-11-28T05:00:13.780Z",
          "status": "down",
          "responseTime": -1
        },
        {
          "timestamp": "2025-11-28T05:30:33.357Z",
          "status": "down",
          "responseTime": -1
        },
        {
          "timestamp": "2025-11-28T05:46:39.389Z",
          "status": "down",
          "responseTime": -1
        },
        {
          "timestamp": "2025-11-28T05:57:27.785Z",
          "status": "down",
          "responseTime": -1
        },
        {
          "timestamp": "2025-11-28T06:40:14.570Z",
          "status": "down",
          "responseTime": -1
        },
        {
          "timestamp": "2025-11-28T06:57:54.409Z",
          "status": "down",
          "responseTime": -1
        },
        {
          "timestamp": "2025-11-28T07:26:57.999Z",
          "status": "down",
          "responseTime": -1
        },
        {
          "timestamp": "2025-11-28T07:41:36.877Z",
          "status": "down",
          "responseTime": -1
        },
        {
          "timestamp": "2025-11-28T07:52:34.757Z",
          "status": "down",
          "responseTime": -1
        },
        {
          "timestamp": "2025-11-28T08:20:46.570Z",
          "status": "down",
          "responseTime": -1
        },
        {
          "timestamp": "2025-11-28T08:46:31.197Z",
          "status": "down",
          "responseTime": -1
        },
        {
          "timestamp": "2025-11-28T09:00:04.805Z",
          "status": "down",
          "responseTime": -1
        },
        {
          "timestamp": "2025-11-28T09:29:59.864Z",
          "status": "down",
          "responseTime": -1
        },
        {
          "timestamp": "2025-11-28T09:44:37.828Z",
          "status": "down",
          "responseTime": -1
        },
        {
          "timestamp": "2025-11-28T09:55:26.327Z",
          "status": "down",
          "responseTime": -1
        },
        {
          "timestamp": "2025-11-28T10:24:34.260Z",
          "status": "down",
          "responseTime": -1
        },
        {
          "timestamp": "2025-11-28T10:44:36.556Z",
          "status": "down",
          "responseTime": -1
        },
        {
          "timestamp": "2025-11-28T10:55:29.994Z",
          "status": "down",
          "responseTime": -1
        },
        {
          "timestamp": "2025-11-28T11:18:55.222Z",
          "status": "down",
          "responseTime": -1
        },
        {
          "timestamp": "2025-11-28T11:31:49.145Z",
          "status": "down",
          "responseTime": -1
        },
        {
          "timestamp": "2025-11-28T11:43:09.638Z",
          "status": "down",
          "responseTime": -1
        },
        {
          "timestamp": "2025-11-28T11:53:59.221Z",
          "status": "down",
          "responseTime": -1
        },
        {
          "timestamp": "2025-11-28T12:37:16.359Z",
          "status": "down",
          "responseTime": -1
        },
        {
          "timestamp": "2025-11-28T13:18:54.866Z",
          "status": "down",
          "responseTime": -1
        },
        {
          "timestamp": "2025-11-28T13:43:54.880Z",
          "status": "down",
          "responseTime": -1
        },
        {
          "timestamp": "2025-11-28T13:54:50.188Z",
          "status": "down",
          "responseTime": -1
        },
        {
          "timestamp": "2025-11-28T14:20:24.755Z",
          "status": "down",
          "responseTime": -1
        },
        {
          "timestamp": "2025-11-28T14:40:26.185Z",
          "status": "down",
          "responseTime": -1
        },
        {
          "timestamp": "2025-11-28T14:51:43.755Z",
          "status": "down",
          "responseTime": -1
        },
        {
          "timestamp": "2025-11-28T15:12:54.581Z",
          "status": "down",
          "responseTime": -1
        },
        {
          "timestamp": "2025-11-28T15:33:22.907Z",
          "status": "down",
          "responseTime": -1
        },
        {
          "timestamp": "2025-11-28T15:46:03.372Z",
          "status": "down",
          "responseTime": -1
        },
        {
          "timestamp": "2025-11-28T15:56:52.327Z",
          "status": "down",
          "responseTime": -1
        },
        {
          "timestamp": "2025-11-28T16:31:11.631Z",
          "status": "down",
          "responseTime": -1
        },
        {
          "timestamp": "2025-11-28T16:49:40.291Z",
          "status": "down",
          "responseTime": -1
        },
        {
          "timestamp": "2025-11-28T17:00:33.334Z",
          "status": "down",
          "responseTime": -1
        },
        {
          "timestamp": "2025-11-28T17:26:27.142Z",
          "status": "down",
          "responseTime": -1
        },
        {
          "timestamp": "2025-11-28T17:41:13.815Z",
          "status": "down",
          "responseTime": -1
        },
        {
          "timestamp": "2025-11-28T17:52:03.760Z",
          "status": "down",
          "responseTime": -1
        },
        {
          "timestamp": "2025-11-28T18:18:56.937Z",
          "status": "down",
          "responseTime": -1
        },
        {
          "timestamp": "2025-11-28T18:44:56.402Z",
          "status": "down",
          "responseTime": -1
        },
        {
          "timestamp": "2025-11-28T18:56:30.442Z",
          "status": "down",
          "responseTime": -1
        },
        {
          "timestamp": "2025-11-28T19:19:09.593Z",
          "status": "down",
          "responseTime": -1
        },
        {
          "timestamp": "2025-11-28T19:29:42.125Z",
          "status": "down",
          "responseTime": -1
        }
      ]
    }
  ],
  "lastUpdated": "2025-11-28T19:29:42.125Z"
}